setup.py
pdr_python_sdk/__init__.py
pdr_python_sdk/client.py
pdr_python_sdk/entity.py
pdr_python_sdk/errors.py
pdr_python_sdk/manager.py
pdr_python_sdk/on_demand_action.py
pdr_python_sdk.egg-info/PKG-INFO
pdr_python_sdk.egg-info/SOURCES.txt
pdr_python_sdk.egg-info/dependency_links.txt
pdr_python_sdk.egg-info/entry_points.txt
pdr_python_sdk.egg-info/requires.txt
pdr_python_sdk.egg-info/top_level.txt
pdr_python_sdk/api/__init__.py
pdr_python_sdk/api/on_demand_api.py
pdr_python_sdk/api/packet.py
pdr_python_sdk/api/response.py
pdr_python_sdk/common/__init__.py
pdr_python_sdk/common/logging.py
pdr_python_sdk/sched_task/__init__.py
pdr_python_sdk/sched_task/on_demand_sched_task.py
pdr_python_sdk/sched_task/sched_task_param.py
pdr_python_sdk/schedule/__init__.py
pdr_python_sdk/schedule/job.py
pdr_python_sdk/schedule/task.py
pdr_python_sdk/spl/__init__.py
pdr_python_sdk/spl/spl_base_command.py
pdr_python_sdk/spl/spl_generating_command.py
pdr_python_sdk/spl/spl_packet_utils.py
pdr_python_sdk/spl/spl_streaming_batch_command.py
pdr_python_sdk/spl/spl_streaming_chunk_command.py
pdr_python_sdk/spl/spl_streaming_command.py
pdr_python_sdk/storage/__init__.py
pdr_python_sdk/storage/base.py
pdr_python_sdk/storage/client.py
pdr_python_sdk/storage/record.py
pdr_python_sdk/tools/__init__.py
pdr_python_sdk/tools/create.py
pdr_python_sdk/tools/mock_tools.py
pdr_python_sdk/tools/upload.py
pdr_python_sdk/trigger_action/__init__.py
pdr_python_sdk/trigger_action/on_demand_trigger_action.py
pdr_python_sdk/trigger_action/trigger_action_param.py